{"@type":"Flow","@id":"c6bc917e-cb79-3b63-8e0c-fb300953e0ab","name":"5-tetradecene, (e)-","description":"From FedElemFlowList_1.2.2. Flow Class: Chemicals. Preferred flow.","category":"Elementary flows/emission/air/troposphere/rural/high","version":"01.02.002","lastChange":"2024-04-26T16:06:11.050Z","flowType":"ELEMENTARY_FLOW","cas":"41446-66-6","formula":"C14H28","synonyms":"5-Tetradecene, (5E)-  ","isInfrastructureFlow":false,"flowProperties":[{"@type":"FlowPropertyFactor","isRefFlowProperty":true,"flowProperty":{"@type":"FlowProperty","@id":"93a60a56-a3c8-11da-a746-0800200b9a66","name":"Mass","category":"Technical flow properties","refUnit":"kg"},"conversionFactor":1.0}]}