{"@type":"Flow","@id":"74ceb705-b776-4c15-8a0d-82956f3e61c6","name":"Transformation, to pasture, man made","category":"Ecosystem Services","version":"00.00.004","lastChange":"2021-07-26T21:58:36.256Z","flowType":"PRODUCT_FLOW","isInfrastructureFlow":false,"flowProperties":[{"@type":"FlowPropertyFactor","isRefFlowProperty":true,"flowProperty":{"@type":"FlowProperty","@id":"93a60a56-a3c8-19da-a746-0800200c9a66","name":"Area","category":"Technical flow properties","refUnit":"m2"},"conversionFactor":1.0}]}