{"@type":"Flow","@id":"4da8510f-e6d8-3640-85fd-5c4ca06cc111","name":"Prochloraz","description":"From FedElemFlowList_1.0.1. Flow Class: Chemicals. Not a preferred flow.","category":"Elementary flows/emission/ground","version":"01.00.001","lastChange":"2020-01-13T21:09:45.589Z","flowType":"ELEMENTARY_FLOW","cas":"67747-09-5","formula":"C15H16Cl3N3O2","isInfrastructureFlow":false,"flowProperties":[{"@type":"FlowPropertyFactor","isRefFlowProperty":true,"flowProperty":{"@type":"FlowProperty","@id":"93a60a56-a3c8-11da-a746-0800200b9a66","name":"Mass","category":"Technical flow properties","refUnit":"kg"},"conversionFactor":1.0}]}