{"@type":"Flow","@id":"630b520b-8281-368a-b33e-d1c2c718dd0e","name":"Pyriproxyfen","description":"From FedElemFlowList_1.0. Flow Class: Chemicals. Not a preferred flow.","category":"Elementary flows/emission/ground","version":"01.00.000","lastChange":"2019-09-11T14:21:13.182Z","flowType":"ELEMENTARY_FLOW","cas":"95737-68-1","formula":"C20H19NO3","isInfrastructureFlow":false,"flowProperties":[{"@type":"FlowPropertyFactor","isRefFlowProperty":true,"flowProperty":{"@type":"FlowProperty","@id":"93a60a56-a3c8-11da-a746-0800200b9a66","name":"Mass","category":"Technical flow properties","refUnit":"kg"},"conversionFactor":1.0}]}