{"@type":"Flow","@id":"2fdec2ef-fd46-3616-a52a-e69b9e447a06","name":"Acetic acid","description":"From FedElemFlowList_1.0. Flow Class: Chemicals. Not a preferred flow.","category":"Elementary flows/emission/water/subterranean/fresh water body","version":"01.00.000","lastChange":"2019-09-11T14:21:41.916Z","flowType":"ELEMENTARY_FLOW","cas":"64-19-7","formula":"C2H4O2","isInfrastructureFlow":false,"flowProperties":[{"@type":"FlowPropertyFactor","isRefFlowProperty":true,"flowProperty":{"@type":"FlowProperty","@id":"93a60a56-a3c8-11da-a746-0800200b9a66","name":"Mass","category":"Technical flow properties","refUnit":"kg"},"conversionFactor":1.0}]}