{"@type":"Flow","@id":"7c699d2a-6812-358b-847f-a7bfe515cd9d","name":"Americium-241","description":"From FedElemFlowList_1.0.1.1. Flow Class: Chemicals. Not a preferred flow.","category":"Elementary flows/emission/water/subterranean/fresh water body","version":"01.00.001","lastChange":"2020-02-21T14:11:45.290Z","flowType":"ELEMENTARY_FLOW","cas":"14596-10-2","formula":"[241Am]","isInfrastructureFlow":false,"flowProperties":[{"@type":"FlowPropertyFactor","flowProperty":{"@type":"FlowProperty","@id":"93a60a56-a3c8-11da-a746-0800200b9a66","name":"Mass","category":"Technical flow properties","refUnit":"kg"},"conversionFactor":7.69E-12},{"@type":"FlowPropertyFactor","isRefFlowProperty":true,"flowProperty":{"@type":"FlowProperty","@id":"93a60a56-a3c8-17da-a746-0800200c9a66","name":"Radioactivity","category":"Technical flow properties","refUnit":"kBq"},"conversionFactor":1.0}]}