{"@type":"Flow","@id":"862a331a-18aa-3acf-be65-b299d40f7dd0","name":"Sulfonic acids, C13-17-sec-alkane, sodium salts","description":"From FedElemFlowList_1.0.3. Flow Class: Chemicals. Not a preferred flow.","category":"Elementary flows/emission/water","version":"01.00.003","lastChange":"2020-04-10T18:08:33.711Z","flowType":"ELEMENTARY_FLOW","cas":"85711-69-9","formula":"-","isInfrastructureFlow":false,"flowProperties":[{"@type":"FlowPropertyFactor","isRefFlowProperty":true,"flowProperty":{"@type":"FlowProperty","@id":"93a60a56-a3c8-11da-a746-0800200b9a66","name":"Mass","category":"Technical flow properties","refUnit":"kg"},"conversionFactor":1.0}]}